// class version 46.0 (46)
// access flags 1
public class com/jsonyao/cs/proxyPattern/HelloCglib$$EnhancerByCGLIB$$6bf7bfad$$FastClassByCGLIB$$9448a271 extends net/sf/cglib/reflect/FastClass  {

  // compiled from: <generated>

  // access flags 1
  public <init>(Ljava/lang/Class;)V
    ALOAD 0
    ALOAD 1
    INVOKESPECIAL net/sf/cglib/reflect/FastClass.<init> (Ljava/lang/Class;)V
    RETURN
    MAXSTACK = 2
    MAXLOCALS = 2

  // access flags 1
  public getIndex(Lnet/sf/cglib/core/Signature;)I
    ALOAD 1
    INVOKEVIRTUAL java/lang/Object.toString ()Ljava/lang/String;
    DUP
    INVOKEVIRTUAL java/lang/Object.hashCode ()I
    LOOKUPSWITCH
      -2055565910: L0
      -1882565338: L1
      -1725733088: L2
      -1512990617: L3
      -1457535688: L4
      -1411842725: L5
      -1026001249: L6
      -894172689: L7
      -792725149: L8
      -623122092: L9
      -419626537: L10
      243996900: L11
      560567118: L12
      811063227: L13
      946854621: L14
      973717575: L15
      1116248544: L16
      1221173700: L17
      1230699260: L18
      1306468936: L19
      1365047848: L20
      1584330438: L21
      1800494055: L22
      1826985398: L23
      1902039948: L24
      1913648695: L25
      1984935277: L26
      default: L27
   L0
    LDC "CGLIB$SET_THREAD_CALLBACKS([Lnet/sf/cglib/proxy/Callback;)V"
    INVOKEVIRTUAL java/lang/Object.equals (Ljava/lang/Object;)Z
    IFEQ L28
    BIPUSH 11
    IRETURN
   L1
    LDC "CGLIB$equals$1(Ljava/lang/Object;)Z"
    INVOKEVIRTUAL java/lang/Object.equals (Ljava/lang/Object;)Z
    IFEQ L28
    BIPUSH 18
    IRETURN
   L2
    LDC "getClass()Ljava/lang/Class;"
    INVOKEVIRTUAL java/lang/Object.equals (Ljava/lang/Object;)Z
    IFEQ L28
    BIPUSH 24
    IRETURN
   L3
    LDC "CGLIB$helloAagin$5()V"
    INVOKEVIRTUAL java/lang/Object.equals (Ljava/lang/Object;)Z
    IFEQ L28
    BIPUSH 16
    IRETURN
   L4
    LDC "CGLIB$STATICHOOK1()V"
    INVOKEVIRTUAL java/lang/Object.equals (Ljava/lang/Object;)Z
    IFEQ L28
    BIPUSH 13
    IRETURN
   L5
    LDC "CGLIB$hashCode$3()I"
    INVOKEVIRTUAL java/lang/Object.equals (Ljava/lang/Object;)Z
    IFEQ L28
    BIPUSH 14
    IRETURN
   L6
    LDC "wait(JI)V"
    INVOKEVIRTUAL java/lang/Object.equals (Ljava/lang/Object;)Z
    IFEQ L28
    BIPUSH 21
    IRETURN
   L7
    LDC "newInstance(Lnet/sf/cglib/proxy/Callback;)Ljava/lang/Object;"
    INVOKEVIRTUAL java/lang/Object.equals (Ljava/lang/Object;)Z
    IFEQ L28
    ICONST_5
    IRETURN
   L8
    LDC "hello()V"
    INVOKEVIRTUAL java/lang/Object.equals (Ljava/lang/Object;)Z
    IFEQ L28
    BIPUSH 20
    IRETURN
   L9
    LDC "CGLIB$findMethodProxy(Lnet/sf/cglib/core/Signature;)Lnet/sf/cglib/proxy/MethodProxy;"
    INVOKEVIRTUAL java/lang/Object.equals (Ljava/lang/Object;)Z
    IFEQ L28
    BIPUSH 19
    IRETURN
   L10
    LDC "setCallbacks([Lnet/sf/cglib/proxy/Callback;)V"
    INVOKEVIRTUAL java/lang/Object.equals (Ljava/lang/Object;)Z
    IFEQ L28
    BIPUSH 9
    IRETURN
   L11
    LDC "wait(J)V"
    INVOKEVIRTUAL java/lang/Object.equals (Ljava/lang/Object;)Z
    IFEQ L28
    BIPUSH 22
    IRETURN
   L12
    LDC "setCallback(ILnet/sf/cglib/proxy/Callback;)V"
    INVOKEVIRTUAL java/lang/Object.equals (Ljava/lang/Object;)Z
    IFEQ L28
    BIPUSH 8
    IRETURN
   L13
    LDC "newInstance([Ljava/lang/Class;[Ljava/lang/Object;[Lnet/sf/cglib/proxy/Callback;)Ljava/lang/Object;"
    INVOKEVIRTUAL java/lang/Object.equals (Ljava/lang/Object;)Z
    IFEQ L28
    ICONST_4
    IRETURN
   L14
    LDC "notifyAll()V"
    INVOKEVIRTUAL java/lang/Object.equals (Ljava/lang/Object;)Z
    IFEQ L28
    BIPUSH 26
    IRETURN
   L15
    LDC "getCallbacks()[Lnet/sf/cglib/proxy/Callback;"
    INVOKEVIRTUAL java/lang/Object.equals (Ljava/lang/Object;)Z
    IFEQ L28
    BIPUSH 6
    IRETURN
   L16
    LDC "wait()V"
    INVOKEVIRTUAL java/lang/Object.equals (Ljava/lang/Object;)Z
    IFEQ L28
    BIPUSH 23
    IRETURN
   L17
    LDC "newInstance([Lnet/sf/cglib/proxy/Callback;)Ljava/lang/Object;"
    INVOKEVIRTUAL java/lang/Object.equals (Ljava/lang/Object;)Z
    IFEQ L28
    ICONST_3
    IRETURN
   L18
    LDC "getCallback(I)Lnet/sf/cglib/proxy/Callback;"
    INVOKEVIRTUAL java/lang/Object.equals (Ljava/lang/Object;)Z
    IFEQ L28
    BIPUSH 7
    IRETURN
   L19
    LDC "CGLIB$toString$2()Ljava/lang/String;"
    INVOKEVIRTUAL java/lang/Object.equals (Ljava/lang/Object;)Z
    IFEQ L28
    BIPUSH 17
    IRETURN
   L20
    LDC "CGLIB$finalize$0()V"
    INVOKEVIRTUAL java/lang/Object.equals (Ljava/lang/Object;)Z
    IFEQ L28
    BIPUSH 15
    IRETURN
   L21
    LDC "CGLIB$SET_STATIC_CALLBACKS([Lnet/sf/cglib/proxy/Callback;)V"
    INVOKEVIRTUAL java/lang/Object.equals (Ljava/lang/Object;)Z
    IFEQ L28
    BIPUSH 10
    IRETURN
   L22
    LDC "CGLIB$clone$4()Ljava/lang/Object;"
    INVOKEVIRTUAL java/lang/Object.equals (Ljava/lang/Object;)Z
    IFEQ L28
    BIPUSH 12
    IRETURN
   L23
    LDC "equals(Ljava/lang/Object;)Z"
    INVOKEVIRTUAL java/lang/Object.equals (Ljava/lang/Object;)Z
    IFEQ L28
    ICONST_0
    IRETURN
   L24
    LDC "notify()V"
    INVOKEVIRTUAL java/lang/Object.equals (Ljava/lang/Object;)Z
    IFEQ L28
    BIPUSH 25
    IRETURN
   L25
    LDC "toString()Ljava/lang/String;"
    INVOKEVIRTUAL java/lang/Object.equals (Ljava/lang/Object;)Z
    IFEQ L28
    ICONST_1
    IRETURN
   L26
    LDC "hashCode()I"
    INVOKEVIRTUAL java/lang/Object.equals (Ljava/lang/Object;)Z
    IFEQ L28
    ICONST_2
    IRETURN
   L27
    POP
   L28
    ICONST_M1
    IRETURN
    MAXSTACK = 2
    MAXLOCALS = 2

  // access flags 1
  public getIndex(Ljava/lang/String;[Ljava/lang/Class;)I
    ALOAD 1
    ALOAD 2
    SWAP
    DUP
    INVOKEVIRTUAL java/lang/Object.hashCode ()I
    LOOKUPSWITCH
      -2083498451: L0
      -1776922004: L1
      -1295482945: L2
      -1053468136: L3
      -1039689911: L4
      -864061362: L5
      -124978609: L6
      -60403779: L7
      -29025555: L8
      3641717: L9
      85179481: L10
      99162322: L11
      147696667: L12
      161998109: L13
      495524492: L14
      1154623345: L15
      1543336189: L16
      1811874389: L17
      1817099975: L18
      1902066072: L19
      1905679803: L20
      1950568386: L21
      1951977610: L22
      default: L23
   L0
    LDC "CGLIB$finalize$0"
    INVOKEVIRTUAL java/lang/Object.equals (Ljava/lang/Object;)Z
    IFEQ L24
    DUP
    ARRAYLENGTH
    TABLESWITCH
      0: L25
      default: L26
   L25
    POP
    BIPUSH 15
    IRETURN
   L26
    GOTO L27
   L1
    LDC "toString"
    INVOKEVIRTUAL java/lang/Object.equals (Ljava/lang/Object;)Z
    IFEQ L24
    DUP
    ARRAYLENGTH
    TABLESWITCH
      0: L28
      default: L29
   L28
    POP
    ICONST_1
    IRETURN
   L29
    GOTO L27
   L2
    LDC "equals"
    INVOKEVIRTUAL java/lang/Object.equals (Ljava/lang/Object;)Z
    IFEQ L24
    DUP
    ARRAYLENGTH
    TABLESWITCH
      1: L30
      default: L31
   L30
    DUP
    ICONST_0
    AALOAD
    INVOKEVIRTUAL java/lang/Class.getName ()Ljava/lang/String;
    LDC "java.lang.Object"
    INVOKEVIRTUAL java/lang/Object.equals (Ljava/lang/Object;)Z
    IFEQ L27
    POP
    ICONST_0
    IRETURN
   L31
    GOTO L27
   L3
    LDC "getCallbacks"
    INVOKEVIRTUAL java/lang/Object.equals (Ljava/lang/Object;)Z
    IFEQ L24
    DUP
    ARRAYLENGTH
    TABLESWITCH
      0: L32
      default: L33
   L32
    POP
    BIPUSH 6
    IRETURN
   L33
    GOTO L27
   L4
    LDC "notify"
    INVOKEVIRTUAL java/lang/Object.equals (Ljava/lang/Object;)Z
    IFEQ L24
    DUP
    ARRAYLENGTH
    TABLESWITCH
      0: L34
      default: L35
   L34
    POP
    BIPUSH 25
    IRETURN
   L35
    GOTO L27
   L5
    LDC "CGLIB$helloAagin$5"
    INVOKEVIRTUAL java/lang/Object.equals (Ljava/lang/Object;)Z
    IFEQ L24
    DUP
    ARRAYLENGTH
    TABLESWITCH
      0: L36
      default: L37
   L36
    POP
    BIPUSH 16
    IRETURN
   L37
    GOTO L27
   L6
    LDC "CGLIB$equals$1"
    INVOKEVIRTUAL java/lang/Object.equals (Ljava/lang/Object;)Z
    IFEQ L24
    DUP
    ARRAYLENGTH
    TABLESWITCH
      1: L38
      default: L39
   L38
    DUP
    ICONST_0
    AALOAD
    INVOKEVIRTUAL java/lang/Class.getName ()Ljava/lang/String;
    LDC "java.lang.Object"
    INVOKEVIRTUAL java/lang/Object.equals (Ljava/lang/Object;)Z
    IFEQ L27
    POP
    BIPUSH 18
    IRETURN
   L39
    GOTO L27
   L7
    LDC "CGLIB$SET_STATIC_CALLBACKS"
    INVOKEVIRTUAL java/lang/Object.equals (Ljava/lang/Object;)Z
    IFEQ L24
    DUP
    ARRAYLENGTH
    TABLESWITCH
      1: L40
      default: L41
   L40
    DUP
    ICONST_0
    AALOAD
    INVOKEVIRTUAL java/lang/Class.getName ()Ljava/lang/String;
    LDC "[Lnet.sf.cglib.proxy.Callback;"
    INVOKEVIRTUAL java/lang/Object.equals (Ljava/lang/Object;)Z
    IFEQ L27
    POP
    BIPUSH 10
    IRETURN
   L41
    GOTO L27
   L8
    LDC "CGLIB$hashCode$3"
    INVOKEVIRTUAL java/lang/Object.equals (Ljava/lang/Object;)Z
    IFEQ L24
    DUP
    ARRAYLENGTH
    TABLESWITCH
      0: L42
      default: L43
   L42
    POP
    BIPUSH 14
    IRETURN
   L43
    GOTO L27
   L9
    LDC "wait"
    INVOKEVIRTUAL java/lang/Object.equals (Ljava/lang/Object;)Z
    IFEQ L24
    DUP
    ARRAYLENGTH
    TABLESWITCH
      0: L44
      1: L45
      2: L46
      default: L47
   L44
    POP
    BIPUSH 23
    IRETURN
   L45
    DUP
    ICONST_0
    AALOAD
    INVOKEVIRTUAL java/lang/Class.getName ()Ljava/lang/String;
    LDC "long"
    INVOKEVIRTUAL java/lang/Object.equals (Ljava/lang/Object;)Z
    IFEQ L27
    POP
    BIPUSH 22
    IRETURN
   L46
    DUP
    ICONST_0
    AALOAD
    INVOKEVIRTUAL java/lang/Class.getName ()Ljava/lang/String;
    LDC "long"
    INVOKEVIRTUAL java/lang/Object.equals (Ljava/lang/Object;)Z
    IFEQ L27
    DUP
    ICONST_1
    AALOAD
    INVOKEVIRTUAL java/lang/Class.getName ()Ljava/lang/String;
    LDC "int"
    INVOKEVIRTUAL java/lang/Object.equals (Ljava/lang/Object;)Z
    IFEQ L27
    POP
    BIPUSH 21
    IRETURN
   L47
    GOTO L27
   L10
    LDC "CGLIB$SET_THREAD_CALLBACKS"
    INVOKEVIRTUAL java/lang/Object.equals (Ljava/lang/Object;)Z
    IFEQ L24
    DUP
    ARRAYLENGTH
    TABLESWITCH
      1: L48
      default: L49
   L48
    DUP
    ICONST_0
    AALOAD
    INVOKEVIRTUAL java/lang/Class.getName ()Ljava/lang/String;
    LDC "[Lnet.sf.cglib.proxy.Callback;"
    INVOKEVIRTUAL java/lang/Object.equals (Ljava/lang/Object;)Z
    IFEQ L27
    POP
    BIPUSH 11
    IRETURN
   L49
    GOTO L27
   L11
    LDC "hello"
    INVOKEVIRTUAL java/lang/Object.equals (Ljava/lang/Object;)Z
    IFEQ L24
    DUP
    ARRAYLENGTH
    TABLESWITCH
      0: L50
      default: L51
   L50
    POP
    BIPUSH 20
    IRETURN
   L51
    GOTO L27
   L12
    LDC "hashCode"
    INVOKEVIRTUAL java/lang/Object.equals (Ljava/lang/Object;)Z
    IFEQ L24
    DUP
    ARRAYLENGTH
    TABLESWITCH
      0: L52
      default: L53
   L52
    POP
    ICONST_2
    IRETURN
   L53
    GOTO L27
   L13
    LDC "CGLIB$STATICHOOK1"
    INVOKEVIRTUAL java/lang/Object.equals (Ljava/lang/Object;)Z
    IFEQ L24
    DUP
    ARRAYLENGTH
    TABLESWITCH
      0: L54
      default: L55
   L54
    POP
    BIPUSH 13
    IRETURN
   L55
    GOTO L27
   L14
    LDC "setCallbacks"
    INVOKEVIRTUAL java/lang/Object.equals (Ljava/lang/Object;)Z
    IFEQ L24
    DUP
    ARRAYLENGTH
    TABLESWITCH
      1: L56
      default: L57
   L56
    DUP
    ICONST_0
    AALOAD
    INVOKEVIRTUAL java/lang/Class.getName ()Ljava/lang/String;
    LDC "[Lnet.sf.cglib.proxy.Callback;"
    INVOKEVIRTUAL java/lang/Object.equals (Ljava/lang/Object;)Z
    IFEQ L27
    POP
    BIPUSH 9
    IRETURN
   L57
    GOTO L27
   L15
    LDC "CGLIB$findMethodProxy"
    INVOKEVIRTUAL java/lang/Object.equals (Ljava/lang/Object;)Z
    IFEQ L24
    DUP
    ARRAYLENGTH
    TABLESWITCH
      1: L58
      default: L59
   L58
    DUP
    ICONST_0
    AALOAD
    INVOKEVIRTUAL java/lang/Class.getName ()Ljava/lang/String;
    LDC "net.sf.cglib.core.Signature"
    INVOKEVIRTUAL java/lang/Object.equals (Ljava/lang/Object;)Z
    IFEQ L27
    POP
    BIPUSH 19
    IRETURN
   L59
    GOTO L27
   L16
    LDC "CGLIB$toString$2"
    INVOKEVIRTUAL java/lang/Object.equals (Ljava/lang/Object;)Z
    IFEQ L24
    DUP
    ARRAYLENGTH
    TABLESWITCH
      0: L60
      default: L61
   L60
    POP
    BIPUSH 17
    IRETURN
   L61
    GOTO L27
   L17
    LDC "newInstance"
    INVOKEVIRTUAL java/lang/Object.equals (Ljava/lang/Object;)Z
    IFEQ L24
    DUP
    ARRAYLENGTH
    TABLESWITCH
      1: L62
      2: L63
      3: L64
      default: L63
   L62
    DUP
    ICONST_0
    AALOAD
    INVOKEVIRTUAL java/lang/Class.getName ()Ljava/lang/String;
    DUP
    INVOKEVIRTUAL java/lang/Object.hashCode ()I
    LOOKUPSWITCH
      -845341380: L65
      1730110032: L66
      default: L67
   L65
    LDC "net.sf.cglib.proxy.Callback"
    INVOKEVIRTUAL java/lang/Object.equals (Ljava/lang/Object;)Z
    IFEQ L68
    POP
    ICONST_5
    IRETURN
   L66
    LDC "[Lnet.sf.cglib.proxy.Callback;"
    INVOKEVIRTUAL java/lang/Object.equals (Ljava/lang/Object;)Z
    IFEQ L68
    POP
    ICONST_3
    IRETURN
   L67
    POP
   L68
    GOTO L27
   L64
    DUP
    ICONST_0
    AALOAD
    INVOKEVIRTUAL java/lang/Class.getName ()Ljava/lang/String;
    LDC "[Ljava.lang.Class;"
    INVOKEVIRTUAL java/lang/Object.equals (Ljava/lang/Object;)Z
    IFEQ L27
    DUP
    ICONST_1
    AALOAD
    INVOKEVIRTUAL java/lang/Class.getName ()Ljava/lang/String;
    LDC "[Ljava.lang.Object;"
    INVOKEVIRTUAL java/lang/Object.equals (Ljava/lang/Object;)Z
    IFEQ L27
    DUP
    ICONST_2
    AALOAD
    INVOKEVIRTUAL java/lang/Class.getName ()Ljava/lang/String;
    LDC "[Lnet.sf.cglib.proxy.Callback;"
    INVOKEVIRTUAL java/lang/Object.equals (Ljava/lang/Object;)Z
    IFEQ L27
    POP
    ICONST_4
    IRETURN
   L63
    GOTO L27
   L18
    LDC "setCallback"
    INVOKEVIRTUAL java/lang/Object.equals (Ljava/lang/Object;)Z
    IFEQ L24
    DUP
    ARRAYLENGTH
    TABLESWITCH
      2: L69
      default: L70
   L69
    DUP
    ICONST_0
    AALOAD
    INVOKEVIRTUAL java/lang/Class.getName ()Ljava/lang/String;
    LDC "int"
    INVOKEVIRTUAL java/lang/Object.equals (Ljava/lang/Object;)Z
    IFEQ L27
    DUP
    ICONST_1
    AALOAD
    INVOKEVIRTUAL java/lang/Class.getName ()Ljava/lang/String;
    LDC "net.sf.cglib.proxy.Callback"
    INVOKEVIRTUAL java/lang/Object.equals (Ljava/lang/Object;)Z
    IFEQ L27
    POP
    BIPUSH 8
    IRETURN
   L70
    GOTO L27
   L19
    LDC "notifyAll"
    INVOKEVIRTUAL java/lang/Object.equals (Ljava/lang/Object;)Z
    IFEQ L24
    DUP
    ARRAYLENGTH
    TABLESWITCH
      0: L71
      default: L72
   L71
    POP
    BIPUSH 26
    IRETURN
   L72
    GOTO L27
   L20
    LDC "getCallback"
    INVOKEVIRTUAL java/lang/Object.equals (Ljava/lang/Object;)Z
    IFEQ L24
    DUP
    ARRAYLENGTH
    TABLESWITCH
      1: L73
      default: L74
   L73
    DUP
    ICONST_0
    AALOAD
    INVOKEVIRTUAL java/lang/Class.getName ()Ljava/lang/String;
    LDC "int"
    INVOKEVIRTUAL java/lang/Object.equals (Ljava/lang/Object;)Z
    IFEQ L27
    POP
    BIPUSH 7
    IRETURN
   L74
    GOTO L27
   L21
    LDC "getClass"
    INVOKEVIRTUAL java/lang/Object.equals (Ljava/lang/Object;)Z
    IFEQ L24
    DUP
    ARRAYLENGTH
    TABLESWITCH
      0: L75
      default: L76
   L75
    POP
    BIPUSH 24
    IRETURN
   L76
    GOTO L27
   L22
    LDC "CGLIB$clone$4"
    INVOKEVIRTUAL java/lang/Object.equals (Ljava/lang/Object;)Z
    IFEQ L24
    DUP
    ARRAYLENGTH
    TABLESWITCH
      0: L77
      default: L78
   L77
    POP
    BIPUSH 12
    IRETURN
   L78
    GOTO L27
   L23
    POP
   L24
    GOTO L27
   L27
    POP
    ICONST_M1
    IRETURN
    MAXSTACK = 3
    MAXLOCALS = 3

  // access flags 1
  public getIndex([Ljava/lang/Class;)I
    ALOAD 1
    DUP
    ARRAYLENGTH
    TABLESWITCH
      0: L0
      default: L1
   L0
    POP
    ICONST_0
    IRETURN
   L1
    GOTO L2
   L2
    POP
    ICONST_M1
    IRETURN
    MAXSTACK = 2
    MAXLOCALS = 2

  // access flags 1
  public invoke(ILjava/lang/Object;[Ljava/lang/Object;)Ljava/lang/Object; throws java/lang/reflect/InvocationTargetException 
    TRYCATCHBLOCK L0 L1 L1 java/lang/Throwable
    ALOAD 2
    CHECKCAST com/jsonyao/cs/proxyPattern/HelloCglib$$EnhancerByCGLIB$$6bf7bfad
    ILOAD 1
   L0
    TABLESWITCH
      0: L2
      1: L3
      2: L4
      3: L5
      4: L6
      5: L7
      6: L8
      7: L9
      8: L10
      9: L11
      10: L12
      11: L13
      12: L14
      13: L15
      14: L16
      15: L17
      16: L18
      17: L19
      18: L20
      19: L21
      20: L22
      21: L23
      22: L24
      23: L25
      24: L26
      25: L27
      26: L28
      default: L29
   L2
    ALOAD 3
    ICONST_0
    AALOAD
    INVOKEVIRTUAL com/jsonyao/cs/proxyPattern/HelloCglib$$EnhancerByCGLIB$$6bf7bfad.equals (Ljava/lang/Object;)Z
    NEW java/lang/Boolean
    DUP_X1
    SWAP
    INVOKESPECIAL java/lang/Boolean.<init> (Z)V
    ARETURN
   L3
    INVOKEVIRTUAL com/jsonyao/cs/proxyPattern/HelloCglib$$EnhancerByCGLIB$$6bf7bfad.toString ()Ljava/lang/String;
    ARETURN
   L4
    INVOKEVIRTUAL com/jsonyao/cs/proxyPattern/HelloCglib$$EnhancerByCGLIB$$6bf7bfad.hashCode ()I
    NEW java/lang/Integer
    DUP_X1
    SWAP
    INVOKESPECIAL java/lang/Integer.<init> (I)V
    ARETURN
   L5
    ALOAD 3
    ICONST_0
    AALOAD
    CHECKCAST [Lnet/sf/cglib/proxy/Callback;
    INVOKEVIRTUAL com/jsonyao/cs/proxyPattern/HelloCglib$$EnhancerByCGLIB$$6bf7bfad.newInstance ([Lnet/sf/cglib/proxy/Callback;)Ljava/lang/Object;
    ARETURN
   L6
    ALOAD 3
    ICONST_0
    AALOAD
    CHECKCAST [Ljava/lang/Class;
    ALOAD 3
    ICONST_1
    AALOAD
    CHECKCAST [Ljava/lang/Object;
    ALOAD 3
    ICONST_2
    AALOAD
    CHECKCAST [Lnet/sf/cglib/proxy/Callback;
    INVOKEVIRTUAL com/jsonyao/cs/proxyPattern/HelloCglib$$EnhancerByCGLIB$$6bf7bfad.newInstance ([Ljava/lang/Class;[Ljava/lang/Object;[Lnet/sf/cglib/proxy/Callback;)Ljava/lang/Object;
    ARETURN
   L7
    ALOAD 3
    ICONST_0
    AALOAD
    CHECKCAST net/sf/cglib/proxy/Callback
    INVOKEVIRTUAL com/jsonyao/cs/proxyPattern/HelloCglib$$EnhancerByCGLIB$$6bf7bfad.newInstance (Lnet/sf/cglib/proxy/Callback;)Ljava/lang/Object;
    ARETURN
   L8
    INVOKEVIRTUAL com/jsonyao/cs/proxyPattern/HelloCglib$$EnhancerByCGLIB$$6bf7bfad.getCallbacks ()[Lnet/sf/cglib/proxy/Callback;
    ARETURN
   L9
    ALOAD 3
    ICONST_0
    AALOAD
    CHECKCAST java/lang/Number
    INVOKEVIRTUAL java/lang/Number.intValue ()I
    INVOKEVIRTUAL com/jsonyao/cs/proxyPattern/HelloCglib$$EnhancerByCGLIB$$6bf7bfad.getCallback (I)Lnet/sf/cglib/proxy/Callback;
    ARETURN
   L10
    ALOAD 3
    ICONST_0
    AALOAD
    CHECKCAST java/lang/Number
    INVOKEVIRTUAL java/lang/Number.intValue ()I
    ALOAD 3
    ICONST_1
    AALOAD
    CHECKCAST net/sf/cglib/proxy/Callback
    INVOKEVIRTUAL com/jsonyao/cs/proxyPattern/HelloCglib$$EnhancerByCGLIB$$6bf7bfad.setCallback (ILnet/sf/cglib/proxy/Callback;)V
    ACONST_NULL
    ARETURN
   L11
    ALOAD 3
    ICONST_0
    AALOAD
    CHECKCAST [Lnet/sf/cglib/proxy/Callback;
    INVOKEVIRTUAL com/jsonyao/cs/proxyPattern/HelloCglib$$EnhancerByCGLIB$$6bf7bfad.setCallbacks ([Lnet/sf/cglib/proxy/Callback;)V
    ACONST_NULL
    ARETURN
   L12
    ALOAD 3
    ICONST_0
    AALOAD
    CHECKCAST [Lnet/sf/cglib/proxy/Callback;
    INVOKESTATIC com/jsonyao/cs/proxyPattern/HelloCglib$$EnhancerByCGLIB$$6bf7bfad.CGLIB$SET_STATIC_CALLBACKS ([Lnet/sf/cglib/proxy/Callback;)V
    ACONST_NULL
    ARETURN
   L13
    ALOAD 3
    ICONST_0
    AALOAD
    CHECKCAST [Lnet/sf/cglib/proxy/Callback;
    INVOKESTATIC com/jsonyao/cs/proxyPattern/HelloCglib$$EnhancerByCGLIB$$6bf7bfad.CGLIB$SET_THREAD_CALLBACKS ([Lnet/sf/cglib/proxy/Callback;)V
    ACONST_NULL
    ARETURN
   L14
    INVOKEVIRTUAL com/jsonyao/cs/proxyPattern/HelloCglib$$EnhancerByCGLIB$$6bf7bfad.CGLIB$clone$4 ()Ljava/lang/Object;
    ARETURN
   L15
    INVOKESTATIC com/jsonyao/cs/proxyPattern/HelloCglib$$EnhancerByCGLIB$$6bf7bfad.CGLIB$STATICHOOK1 ()V
    ACONST_NULL
    ARETURN
   L16
    INVOKEVIRTUAL com/jsonyao/cs/proxyPattern/HelloCglib$$EnhancerByCGLIB$$6bf7bfad.CGLIB$hashCode$3 ()I
    NEW java/lang/Integer
    DUP_X1
    SWAP
    INVOKESPECIAL java/lang/Integer.<init> (I)V
    ARETURN
   L17
    INVOKEVIRTUAL com/jsonyao/cs/proxyPattern/HelloCglib$$EnhancerByCGLIB$$6bf7bfad.CGLIB$finalize$0 ()V
    ACONST_NULL
    ARETURN
   L18
    INVOKEVIRTUAL com/jsonyao/cs/proxyPattern/HelloCglib$$EnhancerByCGLIB$$6bf7bfad.CGLIB$helloAagin$5 ()V
    ACONST_NULL
    ARETURN
   L19
    INVOKEVIRTUAL com/jsonyao/cs/proxyPattern/HelloCglib$$EnhancerByCGLIB$$6bf7bfad.CGLIB$toString$2 ()Ljava/lang/String;
    ARETURN
   L20
    ALOAD 3
    ICONST_0
    AALOAD
    INVOKEVIRTUAL com/jsonyao/cs/proxyPattern/HelloCglib$$EnhancerByCGLIB$$6bf7bfad.CGLIB$equals$1 (Ljava/lang/Object;)Z
    NEW java/lang/Boolean
    DUP_X1
    SWAP
    INVOKESPECIAL java/lang/Boolean.<init> (Z)V
    ARETURN
   L21
    ALOAD 3
    ICONST_0
    AALOAD
    CHECKCAST net/sf/cglib/core/Signature
    INVOKESTATIC com/jsonyao/cs/proxyPattern/HelloCglib$$EnhancerByCGLIB$$6bf7bfad.CGLIB$findMethodProxy (Lnet/sf/cglib/core/Signature;)Lnet/sf/cglib/proxy/MethodProxy;
    ARETURN
   L22
    INVOKEVIRTUAL com/jsonyao/cs/proxyPattern/HelloCglib$$EnhancerByCGLIB$$6bf7bfad.hello ()V
    ACONST_NULL
    ARETURN
   L23
    ALOAD 3
    ICONST_0
    AALOAD
    CHECKCAST java/lang/Number
    INVOKEVIRTUAL java/lang/Number.longValue ()J
    ALOAD 3
    ICONST_1
    AALOAD
    CHECKCAST java/lang/Number
    INVOKEVIRTUAL java/lang/Number.intValue ()I
    INVOKEVIRTUAL com/jsonyao/cs/proxyPattern/HelloCglib$$EnhancerByCGLIB$$6bf7bfad.wait (JI)V
    ACONST_NULL
    ARETURN
   L24
    ALOAD 3
    ICONST_0
    AALOAD
    CHECKCAST java/lang/Number
    INVOKEVIRTUAL java/lang/Number.longValue ()J
    INVOKEVIRTUAL com/jsonyao/cs/proxyPattern/HelloCglib$$EnhancerByCGLIB$$6bf7bfad.wait (J)V
    ACONST_NULL
    ARETURN
   L25
    INVOKEVIRTUAL com/jsonyao/cs/proxyPattern/HelloCglib$$EnhancerByCGLIB$$6bf7bfad.wait ()V
    ACONST_NULL
    ARETURN
   L26
    INVOKEVIRTUAL com/jsonyao/cs/proxyPattern/HelloCglib$$EnhancerByCGLIB$$6bf7bfad.getClass ()Ljava/lang/Class;
    ARETURN
   L27
    INVOKEVIRTUAL com/jsonyao/cs/proxyPattern/HelloCglib$$EnhancerByCGLIB$$6bf7bfad.notify ()V
    ACONST_NULL
    ARETURN
   L28
    INVOKEVIRTUAL com/jsonyao/cs/proxyPattern/HelloCglib$$EnhancerByCGLIB$$6bf7bfad.notifyAll ()V
    ACONST_NULL
    ARETURN
   L29
    GOTO L30
   L1
    NEW java/lang/reflect/InvocationTargetException
    DUP_X1
    SWAP
    INVOKESPECIAL java/lang/reflect/InvocationTargetException.<init> (Ljava/lang/Throwable;)V
    ATHROW
   L30
    NEW java/lang/IllegalArgumentException
    DUP
    LDC "Cannot find matching method/constructor"
    INVOKESPECIAL java/lang/IllegalArgumentException.<init> (Ljava/lang/String;)V
    ATHROW
    MAXSTACK = 5
    MAXLOCALS = 4

  // access flags 1
  public newInstance(I[Ljava/lang/Object;)Ljava/lang/Object; throws java/lang/reflect/InvocationTargetException 
    TRYCATCHBLOCK L0 L1 L1 java/lang/Throwable
    NEW com/jsonyao/cs/proxyPattern/HelloCglib$$EnhancerByCGLIB$$6bf7bfad
    DUP
    ILOAD 1
   L0
    TABLESWITCH
      0: L2
      default: L3
   L2
    INVOKESPECIAL com/jsonyao/cs/proxyPattern/HelloCglib$$EnhancerByCGLIB$$6bf7bfad.<init> ()V
    ARETURN
   L3
    GOTO L4
   L1
    NEW java/lang/reflect/InvocationTargetException
    DUP_X1
    SWAP
    INVOKESPECIAL java/lang/reflect/InvocationTargetException.<init> (Ljava/lang/Throwable;)V
    ATHROW
   L4
    NEW java/lang/IllegalArgumentException
    DUP
    LDC "Cannot find matching method/constructor"
    INVOKESPECIAL java/lang/IllegalArgumentException.<init> (Ljava/lang/String;)V
    ATHROW
    MAXSTACK = 5
    MAXLOCALS = 3

  // access flags 1
  public getMaxIndex()I
    BIPUSH 26
    IRETURN
    MAXSTACK = 1
    MAXLOCALS = 1
}
